fal/__init__.py
fal/__main__.py
fal/_fal_version.py
fal/_serialization.py
fal/_version.py
fal/app.py
fal/apps.py
fal/config.py
fal/container.py
fal/file_sync.py
fal/files.py
fal/flags.py
fal/project.py
fal/py.typed
fal/ref.py
fal/sdk.py
fal/sync.py
fal/upload.py
fal/utils.py
fal/workflows.py
fal/api/__init__.py
fal/api/api.py
fal/api/apps.py
fal/api/client.py
fal/api/deploy.py
fal/api/environments.py
fal/api/keys.py
fal/api/runners.py
fal/api/secrets.py
fal/auth/__init__.py
fal/auth/auth0.py
fal/auth/local.py
fal/cli/__init__.py
fal/cli/_utils.py
fal/cli/api.py
fal/cli/apps.py
fal/cli/auth.py
fal/cli/cli_nested_json.py
fal/cli/create.py
fal/cli/debug.py
fal/cli/deploy.py
fal/cli/doctor.py
fal/cli/environments.py
fal/cli/files.py
fal/cli/keys.py
fal/cli/main.py
fal/cli/parser.py
fal/cli/profile.py
fal/cli/queue.py
fal/cli/run.py
fal/cli/runners.py
fal/cli/secrets.py
fal/cli/teams.py
fal/console/__init__.py
fal/console/icons.py
fal/console/ux.py
fal/distributed/__init__.py
fal/distributed/utils.py
fal/distributed/worker.py
fal/exceptions/__init__.py
fal/exceptions/_base.py
fal/exceptions/_cuda.py
fal/exceptions/auth.py
fal/logging/__init__.py
fal/logging/isolate.py
fal/logging/style.py
fal/logging/trace.py
fal/toolkit/__init__.py
fal/toolkit/compilation.py
fal/toolkit/exceptions.py
fal/toolkit/kv.py
fal/toolkit/optimize.py
fal/toolkit/types.py
fal/toolkit/audio/__init__.py
fal/toolkit/audio/audio.py
fal/toolkit/file/__init__.py
fal/toolkit/file/file.py
fal/toolkit/file/types.py
fal/toolkit/file/providers/fal.py
fal/toolkit/file/providers/gcp.py
fal/toolkit/file/providers/r2.py
fal/toolkit/file/providers/s3.py
fal/toolkit/image/__init__.py
fal/toolkit/image/image.py
fal/toolkit/image/safety_checker.py
fal/toolkit/image/nsfw_filter/__init__.py
fal/toolkit/image/nsfw_filter/env.py
fal/toolkit/image/nsfw_filter/inference.py
fal/toolkit/image/nsfw_filter/model.py
fal/toolkit/image/nsfw_filter/requirements.txt
fal/toolkit/utils/__init__.py
fal-1.69.0.dist-info/METADATA
fal-1.69.0.dist-info/WHEEL
fal-1.69.0.dist-info/entry_points.txt
fal-1.69.0.dist-info/top_level.txt
fal-1.69.0.dist-info/RECORD
