Metadata-Version: 2.4
Name: fal
Version: 1.69.0
Summary: fal is an easy-to-use Serverless Python Framework
Author: Features & Labels <support@fal.ai>
Requires-Python: >=3.8
Requires-Dist: isolate[build]>=0.22.0
Requires-Dist: isolate-proto>=0.29.7
Requires-Dist: grpcio<2,>=1.64.0
Requires-Dist: dill==0.3.7
Requires-Dist: cloudpickle==3.0.0
Requires-Dist: typing-extensions<5,>=4.7.1
Requires-Dist: structlog<26,>=22.3.0
Requires-Dist: opentelemetry-api<2,>=1.15.0
Requires-Dist: opentelemetry-sdk<2,>=1.15.0
Requires-Dist: grpc-interceptor<1,>=0.15.0
Requires-Dist: colorama<1,>=0.4.6
Requires-Dist: portalocker<3,>=2.7.0
Requires-Dist: rich<15,>=13.3.2
Requires-Dist: rich_argparse
Requires-Dist: packaging>=21.3
Requires-Dist: pathspec<1,>=0.11.1
Requires-Dist: pydantic!=2.0.*,!=2.1.*,!=2.2.*,!=2.3.*,!=2.4.*
Requires-Dist: fastapi<0.119,>=0.99.1
Requires-Dist: starlette-exporter>=0.21.0
Requires-Dist: httpx>=0.15.4
Requires-Dist: httpx-sse
Requires-Dist: attrs>=21.3.0
Requires-Dist: python-dateutil<3,>=2.8.0
Requires-Dist: types-python-dateutil<3,>=2.8.0
Requires-Dist: dateparser<2,>=1.2.0
Requires-Dist: types-dateparser<2,>=1.2.0
Requires-Dist: tuspy==1.1.0
Requires-Dist: importlib-metadata>=4.4; python_version < "3.10"
Requires-Dist: msgpack<2,>=1.0.7
Requires-Dist: websockets>=12.0
Requires-Dist: pillow<12,>=10.2.0
Requires-Dist: pyjwt[crypto]<3,>=2.8.0
Requires-Dist: uvicorn<1,>=0.29.0
Requires-Dist: cookiecutter
Requires-Dist: tomli<3,>2
Requires-Dist: tomli-w<2,>=1
Requires-Dist: fsspec
Requires-Dist: tblib<3.2.0
Provides-Extra: docs
Requires-Dist: sphinx<8.2.0; extra == "docs"
Requires-Dist: sphinx-rtd-theme; extra == "docs"
Requires-Dist: sphinx-autodoc-typehints; extra == "docs"
Provides-Extra: test
Requires-Dist: pytest<8; extra == "test"
Requires-Dist: pytest-asyncio; extra == "test"
Requires-Dist: pytest-xdist; extra == "test"
Requires-Dist: pytest-timeout; extra == "test"
Requires-Dist: flaky; extra == "test"
Requires-Dist: boto3; extra == "test"
Requires-Dist: numpy; extra == "test"
Requires-Dist: pyzmq; extra == "test"
Requires-Dist: fal_client; extra == "test"
Provides-Extra: dev
Requires-Dist: fal[docs,test]; extra == "dev"
Requires-Dist: openapi-python-client<1,>=0.14.1; extra == "dev"
